spdl/__init__.py
spdl/py.typed
spdl/_internal/__init__.py
spdl/_internal/import_utils.py
spdl/dataloader/__init__.py
spdl/dataloader/_cache_dataloader.py
spdl/dataloader/_dataloader.py
spdl/dataloader/_pytorch_dataloader.py
spdl/pipeline/__init__.py
spdl/pipeline/_build.py
spdl/pipeline/_builder.py
spdl/pipeline/_pipeline.py
spdl/pipeline/_profile.py
spdl/pipeline/config.py
spdl/pipeline/_common/__init__.py
spdl/pipeline/_common/_convert.py
spdl/pipeline/_common/_misc.py
spdl/pipeline/_common/_source_locator.py
spdl/pipeline/_common/_types.py
spdl/pipeline/_components/__init__.py
spdl/pipeline/_components/_common.py
spdl/pipeline/_components/_hook.py
spdl/pipeline/_components/_node.py
spdl/pipeline/_components/_pipe.py
spdl/pipeline/_components/_queue.py
spdl/pipeline/_components/_sink.py
spdl/pipeline/_components/_source.py
spdl/pipeline/_iter_utils/__init__.py
spdl/pipeline/_iter_utils/_cache_iterator.py
spdl/pipeline/_iter_utils/_common.py
spdl/pipeline/_iter_utils/_subinterpreter.py
spdl/pipeline/_iter_utils/_subprocess.py
spdl/pipeline/defs/__init__.py
spdl/pipeline/defs/_defs.py
spdl/source/__init__.py
spdl/source/_sampler.py
spdl/source/_type.py
spdl/source/imagenet.py
spdl/source/local_directory.py
spdl/source/utils.py
spdl_core-0.2.0.dist-info/licenses/LICENSE
spdl_core-0.2.0.dist-info/METADATA
spdl_core-0.2.0.dist-info/WHEEL
spdl_core-0.2.0.dist-info/top_level.txt
spdl_core-0.2.0.dist-info/RECORD
