Metadata-Version: 2.4
Name: spdl_core
Version: 0.2.0
Summary: SPDL: Scalable and Performant Data Loading.
Author-email: Moto Hira <moto@meta.com>
License-Expression: BSD-2-Clause
Project-URL: Documentation, https://facebookresearch.github.io/spdl/main/index.html
Requires-Python: >=3.10
License-File: LICENSE
Dynamic: license-file
